prossa/__init__.py
prossa/__main__.py
prossa/analyzer.py
prossa/config.toml
prossa/utils.py
prossa-1.4.0.dist-info/LICENSE
prossa-1.4.0.dist-info/METADATA
prossa-1.4.0.dist-info/WHEEL
prossa-1.4.0.dist-info/entry_points.txt
prossa-1.4.0.dist-info/top_level.txt
prossa-1.4.0.dist-info/RECORD
