Metadata-Version: 2.1
Name: prossa
Version: 1.4.0
Summary: An open-source library for checking data preprocessing techniques applicable on a dataset.
Author-email: Fosberg Addai <fosberg1addai@gmail.com>
License: MIT License
Project-URL: Homepage, https://github.com/yourusername/prossa
Keywords: data,analysis,preprocessing,Machine Learning
Classifier: License :: OSI Approved :: MIT License
Classifier: Programming Language :: Python
Classifier: Programming Language :: Python :: 3
Requires-Python: >=3.7
License-File: LICENSE
Requires-Dist: pandas
Requires-Dist: numpy
Requires-Dist: scipy
Provides-Extra: dev
Requires-Dist: pytest; extra == "dev"
Requires-Dist: pip-tools; extra == "dev"
Requires-Dist: bumpver; extra == "dev"
Provides-Extra: test
Requires-Dist: pytest; extra == "test"
Requires-Dist: pip-tools; extra == "test"
Requires-Dist: bumpver; extra == "test"
Provides-Extra: where
Requires-Dist: src; extra == "where"
